auditwheel/__init__.py
auditwheel/__main__.py
auditwheel/architecture.py
auditwheel/condatools.py
auditwheel/elfutils.py
auditwheel/error.py
auditwheel/genericpkgctx.py
auditwheel/hashfile.py
auditwheel/json.py
auditwheel/lddtree.py
auditwheel/libc.py
auditwheel/main.py
auditwheel/main_lddtree.py
auditwheel/main_repair.py
auditwheel/main_show.py
auditwheel/patcher.py
auditwheel/repair.py
auditwheel/sboms.py
auditwheel/tmpdirs.py
auditwheel/tools.py
auditwheel/wheel_abi.py
auditwheel/wheeltools.py
auditwheel/_vendor/__init__.py
auditwheel/_vendor/wheel/LICENSE.txt
auditwheel/_vendor/wheel/__init__.py
auditwheel/_vendor/wheel/pkginfo.py
auditwheel/_vendor/whichprovides/LICENSE.txt
auditwheel/_vendor/whichprovides/__init__.py
auditwheel/_vendor/whichprovides/__main__.py
auditwheel/policy/__init__.py
auditwheel/policy/manylinux-policy.json
auditwheel/policy/musllinux-policy.json
auditwheel-6.6.0.dist-info/licenses/LICENSE
auditwheel-6.6.0.dist-info/METADATA
auditwheel-6.6.0.dist-info/WHEEL
auditwheel-6.6.0.dist-info/entry_points.txt
auditwheel-6.6.0.dist-info/top_level.txt
auditwheel-6.6.0.dist-info/RECORD
