Metadata-Version: 2.4
Name: auditwheel
Version: 6.6.0
Summary: Cross-distribution Linux wheels
Author-email: "Robert T. McGibbon" <rmcgibbo@gmail.com>
License: MIT
Project-URL: Homepage, https://github.com/pypa/auditwheel
Classifier: Development Status :: 4 - Beta
Classifier: Environment :: Console
Classifier: Intended Audience :: Developers
Classifier: License :: OSI Approved :: MIT License
Classifier: Operating System :: POSIX :: Linux
Classifier: Programming Language :: Python :: 3
Classifier: Programming Language :: Python :: 3.10
Classifier: Programming Language :: Python :: 3.11
Classifier: Programming Language :: Python :: 3.12
Classifier: Programming Language :: Python :: 3.13
Classifier: Programming Language :: Python :: 3.14
Classifier: Programming Language :: Python :: 3 :: Only
Classifier: Topic :: Software Development
Classifier: Topic :: Software Development :: Build Tools
Classifier: Topic :: Software Development :: Libraries :: Python Modules
Requires-Python: >=3.10
License-File: LICENSE
Requires-Dist: packaging>=20.9
Requires-Dist: pyelftools>=0.24
Dynamic: license-file
